{"/m/you_are_so_not_invited_to_my_bat_mitzvah":{"name":"You Are So Not Invited to My Bat Mitzvah","href":"/m/you_are_so_not_invited_to_my_bat_mitzvah","year":"(2023)","score":"rotten"},"/m/heart_of_stone_2023":{"name":"Heart of Stone","href":"/m/heart_of_stone_2023","year":"(2023)","score":"rotten"},"/m/the_last_voyage_of_the_demeter":{"name":"The Last Voyage of the Demeter","href":"/m/the_last_voyage_of_the_demeter","year":"(2023)","score":"fresh"},"/m/meg_2_the_trench":{"name":"Meg 2: The Trench","href":"/m/meg_2_the_trench","year":"(2023)","score":"rotten"},"/m/teenage_mutant_ninja_turtles_mutant_mayhem":{"name":"Teenage Mutant Ninja Turtles: Mutant Mayhem","href":"/m/teenage_mutant_ninja_turtles_mutant_mayhem","year":"(2023)","score":"fresh"},"/m/talk_to_me_2023":{"name":"Talk to Me","href":"/m/talk_to_me_2023","year":"(2023)","score":"fresh"},"/m/barbie":{"name":"Barbie","href":"/m/barbie","year":"(2023)","score":"fresh"},"/m/oppenheimer_2023":{"name":"Oppenheimer","href":"/m/oppenheimer_2023","year":"(2023)","score":"fresh"},"/m/sound_of_freedom":{"name":"Sound of Freedom","href":"/m/sound_of_freedom","year":"(2022)","score":"rotten"},"/m/mission_impossible_dead_reckoning_part_one":{"name":"Mission: Impossible - Dead Reckoning, Part One","href":"/m/mission_impossible_dead_reckoning_part_one","year":"(2023)","score":"fresh"},"/m/the_burbs":{"name":"The 'Burbs","href":"/m/the_burbs","year":"(1989)","score":"fresh"},"/m/indiana_jones_and_the_dial_of_destiny":{"name":"Indiana Jones and the Dial of Destiny","href":"/m/indiana_jones_and_the_dial_of_destiny","year":"(2023)","score":"rotten"},"/m/the_blackening":{"name":"The Blackening","href":"/m/the_blackening","year":"(2022)","score":"rotten"},"/m/elemental_2023":{"name":"Elemental","href":"/m/elemental_2023","year":"(2023)","score":"fresh"},"/m/the_flash_2023":{"name":"The Flash","href":"/m/the_flash_2023","year":"(2023)","score":"fresh"},"/m/asteroid_city":{"name":"Asteroid City","href":"/m/asteroid_city","year":"(2023)","score":"rotten"},"/m/no_hard_feelings_2023":{"name":"No Hard Feelings","href":"/m/no_hard_feelings_2023","year":"(2023)","score":"fresh"},"/m/transformers_rise_of_the_beasts":{"name":"Transformers: Rise of the Beasts","href":"/m/transformers_rise_of_the_beasts","year":"(2023)","score":"rotten"},"/m/spider_man_across_the_spider_verse":{"name":"Spider-Man: Across the Spider-Verse","href":"/m/spider_man_across_the_spider_verse","year":"(2023)","score":"fresh"},"/m/the_little_mermaid_2023":{"name":"The Little Mermaid","href":"/m/the_little_mermaid_2023","year":"(2023)","score":"rotten"},"/m/guardians_of_the_galaxy_vol_3":{"name":"Guardians of the Galaxy Vol. 3","href":"/m/guardians_of_the_galaxy_vol_3","year":"(2023)","score":"fresh"},"/m/evil_dead_rise":{"name":"Evil Dead Rise","href":"/m/evil_dead_rise","year":"(2023)","score":"fresh"},"/m/renfield":{"name":"Renfield","href":"/m/renfield","year":"(2023)","score":"rotten"},"/m/the_super_mario_bros_movie":{"name":"The Super Mario Bros. Movie","href":"/m/the_super_mario_bros_movie","year":"(2023)","score":"fresh"},"/m/65":{"name":"65","href":"/m/65","year":"(2023)","score":"fresh"},"/m/scream_vi":{"name":"Scream VI","href":"/m/scream_vi","year":"(2023)","score":"fresh"},"/m/creed_iii":{"name":"Creed III","href":"/m/creed_iii","year":"(2023)","score":"fresh"},"/m/winnie_the_pooh_blood_and_honey":{"name":"Winnie-the-Pooh: Blood and Honey","href":"/m/winnie_the_pooh_blood_and_honey","year":"(2023)","score":"rotten"},"/m/ant_man_and_the_wasp_quantumania":{"name":"Ant-Man and The Wasp: Quantumania","href":"/m/ant_man_and_the_wasp_quantumania","year":"(2023)","score":"rotten"},"/m/white_noise_2022":{"name":"White Noise","href":"/m/white_noise_2022","year":"(2022)","score":"rotten"},"/m/m3gan":{"name":"M3GAN","href":"/m/m3gan","year":"(2022)","score":"fresh"},"/m/glass_onion_a_knives_out_mystery":{"name":"Glass Onion: A Knives Out Mystery","href":"/m/glass_onion_a_knives_out_mystery","year":"(2022)","score":"fresh"},"/m/babylon_2022":{"name":"Babylon","href":"/m/babylon_2022","year":"(2022)","score":"fresh"},"/m/avatar_the_way_of_water":{"name":"Avatar: The Way of Water","href":"/m/avatar_the_way_of_water","year":"(2022)","score":"rotten"},"/m/violent_night":{"name":"Violent Night","href":"/m/violent_night","year":"(2022)","score":"fresh"},"/m/disenchanted_2022":{"name":"Disenchanted","href":"/m/disenchanted_2022","year":"(2022)","score":"rotten"},"/m/strange_world":{"name":"Strange World","href":"/m/strange_world","year":"(2022)","score":"fresh"},"/m/the_menu":{"name":"The Menu","href":"/m/the_menu","year":"(2022)","score":"fresh"},"/m/black_panther_wakanda_forever":{"name":"Black Panther: Wakanda Forever","href":"/m/black_panther_wakanda_forever","year":"(2022)","score":"rotten"},"/m/spirited":{"name":"Spirited","href":"/m/spirited","year":"(2022)","score":"rotten"},"/m/black_adam":{"name":"Black Adam","href":"/m/black_adam","year":"(2022)","score":"rotten"},"/m/hellraiser_2022":{"name":"Hellraiser","href":"/m/hellraiser_2022","year":"(2022)","score":"rotten"},"/m/halloween_ends":{"name":"Halloween Ends","href":"/m/halloween_ends","year":"(2022)","score":"fresh"},"/m/hocus_pocus_2":{"name":"Hocus Pocus 2","href":"/m/hocus_pocus_2","year":"(2022)","score":"rotten"},"/m/pinocchio_2022":{"name":"Pinocchio","href":"/m/pinocchio_2022","year":"(2022)","score":"rotten"},"/m/fall":{"name":"Fall","href":"/m/fall","year":"(2022)","score":"fresh"},"/m/smile_2022":{"name":"Smile","href":"/m/smile_2022","year":"(2022)","score":"fresh"},"/m/blonde":{"name":"Blonde","href":"/m/blonde","year":"(2022)","score":"rotten"},"/m/dont_worry_darling":{"name":"Don't Worry Darling","href":"/m/dont_worry_darling","year":"(2022)","score":"rotten"},"/m/the_matrix_resurrections":{"name":"The Matrix Resurrections","href":"/m/the_matrix_resurrections","year":"(2021)","score":"rotten"}}