{"/m/teenage_mutant_ninja_turtles_mutant_mayhem":{"name":"Teenage Mutant Ninja Turtles: Mutant Mayhem","href":"/m/teenage_mutant_ninja_turtles_mutant_mayhem","year":"(2023)","score":"fresh"},"/m/red_white_and_royal_blue":{"name":"Red, White & Royal Blue","href":"/m/red_white_and_royal_blue","year":"(2023)","score":"fresh"},"/m/haunted_mansion_2023":{"name":"Haunted Mansion","href":"/m/haunted_mansion_2023","year":"(2023)","score":"rotten"},"/m/barbie":{"name":"Barbie","href":"/m/barbie","year":"(2023)","score":"fresh"},"/m/county_lines":{"name":"County Lines","href":"/m/county_lines","year":"(2019)","score":"fresh"},"/m/the_unbearable_weight_of_massive_talent":{"name":"The Unbearable Weight of Massive Talent","href":"/m/the_unbearable_weight_of_massive_talent","year":"(2022)","score":"fresh"},"/m/fire_of_love":{"name":"Fire of Love","href":"/m/fire_of_love","year":"(2022)","score":"fresh"},"/m/velvet_goldmine":{"name":"Velvet Goldmine","href":"/m/velvet_goldmine","year":"(1998)","score":"fresh"},"/m/see_how_they_run":{"name":"See How They Run","href":"/m/see_how_they_run","year":"(2022)","score":"fresh"},"/m/wendell_and_wild":{"name":"Wendell & Wild","href":"/m/wendell_and_wild","year":"(2022)","score":"fresh"},"/m/sicario_2015":{"name":"Sicario","href":"/m/sicario_2015","year":"(2015)","score":"fresh"},"/m/about_time":{"name":"About Time","href":"/m/about_time","year":"(2013)","score":"fresh"},"/m/wedding_season":{"name":"Wedding Season","href":"/m/wedding_season","year":"(2022)","score":"fresh"},"/m/prey_2022":{"name":"Prey","href":"/m/prey_2022","year":"(2022)","score":"fresh"},"/m/a_secret_love":{"name":"A Secret Love","href":"/m/a_secret_love","year":"(2020)","score":"fresh"},"/m/the_lunchbox":{"name":"The Lunchbox","href":"/m/the_lunchbox","year":"(2013)","score":"fresh"},"/m/pride_2014":{"name":"Pride","href":"/m/pride_2014","year":"(2014)","score":"fresh"},"/m/good_vibrations_2012":{"name":"Good Vibrations","href":"/m/good_vibrations_2012","year":"(2012)","score":"fresh"},"/m/instant_family":{"name":"Instant Family","href":"/m/instant_family","year":"(2018)","score":"fresh"},"/m/set_it_up":{"name":"Set It Up","href":"/m/set_it_up","year":"(2018)","score":"fresh"},"/m/boys_state":{"name":"Boys State","href":"/m/boys_state","year":"(2020)","score":"fresh"},"/m/son_of_rambow":{"name":"Son of Rambow","href":"/m/son_of_rambow","year":"(2007)","score":"fresh"},"/m/everything_everywhere_all_at_once":{"name":"Everything Everywhere All at Once","href":"/m/everything_everywhere_all_at_once","year":"(2022)","score":"fresh"},"/m/the_lost_city":{"name":"The Lost City","href":"/m/the_lost_city","year":"(2022)","score":"fresh"},"/m/the_northman":{"name":"The Northman","href":"/m/the_northman","year":"(2022)","score":"fresh"},"/m/somethings_gotta_give":{"name":"Something's Gotta Give","href":"/m/somethings_gotta_give","year":"(2003)","score":"fresh"},"/m/1108206-evolution":{"name":"Evolution","href":"/m/1108206-evolution","year":"(2001)","score":"fresh"},"/m/midnight_special_2015":{"name":"Midnight Special","href":"/m/midnight_special_2015","year":"(2016)","score":"fresh"},"/m/force_majeure_2014":{"name":"Force majeure\t","href":"/m/force_majeure_2014","year":"(2014)","score":"fresh"},"/m/summerland_2020":{"name":"Summerland","href":"/m/summerland_2020","year":"(2020)","score":"fresh"},"/m/stardust":{"name":"Stardust","href":"/m/stardust","year":"(2007)","score":"fresh"},"/m/his_girl_friday":{"name":"His Girl Friday","href":"/m/his_girl_friday","year":"(1940)","score":"fresh"},"/m/the_last_5_years":{"name":"The Last Five Years","href":"/m/the_last_5_years","year":"(2014)","score":"fresh"},"/m/personal_shopper":{"name":"Personal Shopper","href":"/m/personal_shopper","year":"(2016)","score":"fresh"},"/m/logan_lucky":{"name":"Logan Lucky","href":"/m/logan_lucky","year":"(2017)","score":"fresh"},"/m/1003707-casablanca":{"name":"Casablanca","href":"/m/1003707-casablanca","year":"(1942)","score":"fresh"},"/m/1095420-high_fidelity":{"name":"High Fidelity","href":"/m/1095420-high_fidelity","year":"(2000)","score":"fresh"},"/m/rocky_horror_picture_show":{"name":"The Rocky Horror Picture Show","href":"/m/rocky_horror_picture_show","year":"(1975)","score":"fresh"},"/m/the_founder":{"name":"The Founder","href":"/m/the_founder","year":"(2016)","score":"fresh"},"/m/beast":{"name":"Beast","href":"/m/beast","year":"(2017)","score":"fresh"},"/m/barb_and_star_go_to_vista_del_mar":{"name":"Barb & Star Go to Vista Del Mar","href":"/m/barb_and_star_go_to_vista_del_mar","year":"(2021)","score":"fresh"},"/m/i_capture_the_castle":{"name":"I Capture the Castle","href":"/m/i_capture_the_castle","year":"(2003)","score":"fresh"},"/m/summer_of_soul":{"name":"Summer of Soul (...Or, When the Revolution Could Not Be Televised)","href":"/m/summer_of_soul","year":"(2021)","score":"fresh"},"/m/1164675-anita_and_me":{"name":"Anita & Me","href":"/m/1164675-anita_and_me","year":"(2002)","score":"fresh"},"/m/the_red_turtle":{"name":"The Red Turtle","href":"/m/the_red_turtle","year":"(2016)","score":"fresh"},"/m/bpm":{"name":"BPM (Beats Per Minute)","href":"/m/bpm","year":"(2017)","score":"fresh"},"/m/rosie_2019":{"name":"Rosie","href":"/m/rosie_2019","year":"(2018)","score":"fresh"},"/m/kinky_boots":{"name":"Kinky Boots","href":"/m/kinky_boots","year":"(2005)","score":"fresh"},"/m/1218217-single_man":{"name":"A Single Man","href":"/m/1218217-single_man","year":"(2009)","score":"fresh"},"/m/the_intern":{"name":"The Intern","href":"/m/the_intern","year":"(2015)","score":"fresh"}}