{"/m/the_fabelmans":{"name":"The Fabelmans","href":"/m/the_fabelmans","year":"(2022)","score":"fresh"},"/m/it_must_be_heaven":{"name":"It Must Be Heaven","href":"/m/it_must_be_heaven","year":"(2019)","score":"fresh"},"/m/bad_trip_2020":{"name":"Bad Trip","href":"/m/bad_trip_2020","year":"(2021)","score":"fresh"},"/m/the_dissident":{"name":"The Dissident","href":"/m/the_dissident","year":"(2020)","score":"fresh"},"/m/beasts_clawing_at_straws":{"name":"Beasts Clawing at Straws","href":"/m/beasts_clawing_at_straws","year":"(2020)","score":"fresh"},"/m/kubrick_by_kubrick":{"name":"Kubrick by Kubrick","href":"/m/kubrick_by_kubrick","year":"(2020)","score":"fresh"},"/m/cats_2019":{"name":"Cats","href":"/m/cats_2019","year":"(2019)","score":"rotten"},"/m/glass_2019":{"name":"Glass","href":"/m/glass_2019","year":"(2019)","score":"rotten"},"/m/the_meeting_2018":{"name":"The Meeting","href":"/m/the_meeting_2018","year":"(2018)","score":"fresh"},"/m/blackkklansman":{"name":"BlacKkKlansman","href":"/m/blackkklansman","year":"(2018)","score":"fresh"},"/m/the_breadwinner":{"name":"The Breadwinner","href":"/m/the_breadwinner","year":"(2017)","score":"fresh"},"/m/isle_of_dogs_2018":{"name":"Isle of Dogs","href":"/m/isle_of_dogs_2018","year":"(2018)","score":"fresh"}}