{"/m/heart_parade":{"name":"Heart Parade","href":"/m/heart_parade","year":"(2022)","score":"rotten"},"/m/fck_love_too":{"name":"F*ck Love Too","href":"/m/fck_love_too","year":"(2022)","score":"rotten"},"/m/dancing_on_glass":{"name":"Dancing on Glass","href":"/m/dancing_on_glass","year":"(2022)","score":"fresh"},"/m/child_of_kamiari_month":{"name":"Child of Kamiari Month","href":"/m/child_of_kamiari_month","year":"(2021)","score":"fresh"},"/m/mother_android":{"name":"Mother/Android","href":"/m/mother_android","year":"(2021)","score":"rotten"},"/m/the_whole_truth_2021":{"name":"The Whole Truth","href":"/m/the_whole_truth_2021","year":"(2021)","score":"rotten"},"/m/a_castle_for_christmas":{"name":"A Castle for Christmas","href":"/m/a_castle_for_christmas","year":"(2021)","score":"fresh"},"/m/love_hard":{"name":"Love Hard","href":"/m/love_hard","year":"(2021)","score":"fresh"},"/m/hypnotic":{"name":"Hypnotic","href":"/m/hypnotic","year":"(2021)","score":"fresh"},"/m/resort_to_love":{"name":"Resort to Love","href":"/m/resort_to_love","year":"(2021)","score":"rotten"},"/m/words_bubble_up_like_soda_pop":{"name":"Words Bubble Up Like Soda Pop","href":"/m/words_bubble_up_like_soda_pop","year":"(2020)","score":"fresh"},"/m/dancing_queens_2021":{"name":"Dancing Queens","href":"/m/dancing_queens_2021","year":"(2021)","score":"fresh"},"/m/pretty_guardian_sailor_moon_eternal_the_movie":{"name":"Pretty Guardian Sailor Moon Eternal The Movie","href":"/m/pretty_guardian_sailor_moon_eternal_the_movie","year":"(2021)","score":"fresh"},"/m/the_strange_house":{"name":"The Strange House","href":"/m/the_strange_house","year":"(2020)","score":"rotten"},"/m/ferry":{"name":"Ferry","href":"/m/ferry","year":"(2021)","score":"fresh"},"/m/i_am_all_girls":{"name":"I Am All Girls","href":"/m/i_am_all_girls","year":"(2021)","score":"fresh"},"/m/the_disciple_2020":{"name":"The Disciple","href":"/m/the_disciple_2020","year":"(2020)","score":"fresh"},"/m/things_heard_and_seen":{"name":"Things Heard & Seen","href":"/m/things_heard_and_seen","year":"(2021)","score":"rotten"},"/m/ajeeb_daastaans":{"name":"Ajeeb Daastaans","href":"/m/ajeeb_daastaans","year":"(2021)","score":"fresh"},"/m/arlo_the_alligator_boy":{"name":"Arlo the Alligator Boy","href":"/m/arlo_the_alligator_boy","year":"(2021)","score":"fresh"},"/m/into_the_beat":{"name":"Into the Beat","href":"/m/into_the_beat","year":"(2019)","score":"fresh"},"/m/the_soul":{"name":"The Soul","href":"/m/the_soul","year":"(2021)","score":"fresh"},"/m/new_gods_nezha_reborn":{"name":"New Gods: Nezha Reborn","href":"/m/new_gods_nezha_reborn","year":"(2021)","score":"fresh"},"/m/a_week_away":{"name":"A Week Away","href":"/m/a_week_away","year":"(2021)","score":"rotten"},"/m/bad_trip_2020":{"name":"Bad Trip","href":"/m/bad_trip_2020","year":"(2021)","score":"fresh"},"/m/nate_bargatze_the_greatest_average_american":{"name":"Nate Bargatze: The Greatest Average American","href":"/m/nate_bargatze_the_greatest_average_american","year":"(2021)","score":"fresh"},"/m/slaxx":{"name":"Slaxx","href":"/m/slaxx","year":"(2020)","score":"fresh"},"/m/operation_varsity_blues_the_college_admissions_scandal":{"name":"Operation Varsity Blues: The College Admissions Scandal","href":"/m/operation_varsity_blues_the_college_admissions_scandal","year":"(2021)","score":"fresh"},"/m/coven_of_sisters":{"name":"Coven of Sisters","href":"/m/coven_of_sisters","year":"(2020)","score":"fresh"},"/m/sentinelle":{"name":"Sentinelle","href":"/m/sentinelle","year":"(2021)","score":"fresh"},"/m/biggie_i_got_a_story_to_tell":{"name":"Biggie: I Got a Story to Tell","href":"/m/biggie_i_got_a_story_to_tell","year":"(2021)","score":"fresh"},"/m/geez_and_ann":{"name":"Geez & Ann","href":"/m/geez_and_ann","year":"(2021)","score":"rotten"},"/m/xicos_journey":{"name":"Xico's Journey","href":"/m/xicos_journey","year":"(2020)","score":"rotten"},"/m/layla_majnun":{"name":"Layla Majnun","href":"/m/layla_majnun","year":"(2021)","score":"fresh"},"/m/squared_love":{"name":"Squared Love","href":"/m/squared_love","year":"(2021)","score":"fresh"},"/m/the_misadventures_of_hedi_and_cokeman":{"name":"The Misadventures of Hedi and Cokeman","href":"/m/the_misadventures_of_hedi_and_cokeman","year":"(2021)","score":"rotten"},"/m/the_last_paradiso":{"name":"The Last Paradiso","href":"/m/the_last_paradiso","year":"(2020)","score":"rotten"},"/m/space_sweepers":{"name":"Space Sweepers","href":"/m/space_sweepers","year":"(2021)","score":"fresh"},"/m/the_yin_yang_master_dream_of_eternity":{"name":"The Yin-Yang Master: Dream of Eternity","href":"/m/the_yin_yang_master_dream_of_eternity","year":"(2021)","score":"rotten"},"/m/all_my_friends_are_dead":{"name":"All My Friends Are Dead","href":"/m/all_my_friends_are_dead","year":"(2020)","score":"fresh"},"/m/penguin_bloom":{"name":"Penguin Bloom","href":"/m/penguin_bloom","year":"(2020)","score":"rotten"},"/m/so_my_grandmas_a_lesbian":{"name":"So, My Grandma's a Lesbian!","href":"/m/so_my_grandmas_a_lesbian","year":"(2019)","score":"fresh"},"/m/tribhanga_tedhi_medhi_crazy":{"name":"Tribhanga: Tedhi Medhi Crazy","href":"/m/tribhanga_tedhi_medhi_crazy","year":"(2021)","score":"fresh"},"/m/giving_voice":{"name":"Giving Voice","href":"/m/giving_voice","year":"(2020)","score":"fresh"},"/m/the_prom_2020":{"name":"The Prom","href":"/m/the_prom_2020","year":"(2020)","score":"rotten"},"/m/funny_boy_2020":{"name":"Funny Boy","href":"/m/funny_boy_2020","year":"(2020)","score":"fresh"},"/m/christmas_crossfire":{"name":"Wir Können Nicht Anders","href":"/m/christmas_crossfire","year":"(2020)","score":"fresh"},"/m/leyla_everlasting":{"name":"Leyla Everlasting","href":"/m/leyla_everlasting","year":"(2020)","score":"rotten"},"/m/angelas_christmas_wish":{"name":"Angela's Christmas Wish","href":"/m/angelas_christmas_wish","year":"(2020)","score":"fresh"},"/m/dont_listen":{"name":"Don't Listen","href":"/m/dont_listen","year":"(2020)","score":"rotten"}}