{"/m/mascarade":{"name":"Mascarade","href":"/m/mascarade","year":"(2022)","score":"rotten"},"/m/epic_tails":{"name":"Epic Tails","href":"/m/epic_tails","year":"(2022)","score":"fresh"},"/m/plan_75":{"name":"Plan 75","href":"/m/plan_75","year":"(2022)","score":"rotten"},"/m/return_to_seoul":{"name":"Return to Seoul","href":"/m/return_to_seoul","year":"(2022)","score":"fresh"},"/m/eden_2022":{"name":"Edén","href":"/m/eden_2022","year":"(2022)","score":"fresh"},"/m/aftersun":{"name":"Aftersun","href":"/m/aftersun","year":"(2022)","score":"fresh"},"/m/close_2022":{"name":"Close","href":"/m/close_2022","year":"(2022)","score":"fresh"},"/m/wendell_and_wild":{"name":"Wendell & Wild","href":"/m/wendell_and_wild","year":"(2022)","score":"fresh"},"/m/raymond_and_ray":{"name":"Raymond & Ray","href":"/m/raymond_and_ray","year":"(2022)","score":"rotten"},"/m/cadejo_blanco":{"name":"Cadejo Blanco","href":"/m/cadejo_blanco","year":"(2021)","score":"fresh"},"/m/42_segundos":{"name":"42 segundos","href":"/m/42_segundos","year":"(2022)","score":"fresh"},"/m/undercover_2021":{"name":"Undercover","href":"/m/undercover_2021","year":"(2021)","score":"fresh"},"/m/ninjababy":{"name":"Ninjababy","href":"/m/ninjababy","year":"(2021)","score":"fresh"},"/m/live_is_life":{"name":"Live is Life","href":"/m/live_is_life","year":"(2021)","score":"fresh"},"/m/knock_knock_its_mom":{"name":"Knock, Knock, It's Mom!","href":"/m/knock_knock_its_mom","year":"(2020)","score":"rotten"},"/m/black_box_2021":{"name":"Black Box","href":"/m/black_box_2021","year":"(2021)","score":"fresh"},"/m/ghostbusters_afterlife":{"name":"Ghostbusters: Afterlife","href":"/m/ghostbusters_afterlife","year":"(2021)","score":"fresh"},"/m/next_door_2021":{"name":"Next Door","href":"/m/next_door_2021","year":"(2021)","score":"fresh"},"/m/petite_maman":{"name":"Petite Maman","href":"/m/petite_maman","year":"(2021)","score":"fresh"},"/m/calamity":{"name":"Calamity","href":"/m/calamity","year":"(2020)","score":"fresh"},"/m/after_we_fell":{"name":"After We Fell","href":"/m/after_we_fell","year":"(2021)","score":"rotten"},"/m/true_mothers":{"name":"True Mothers","href":"/m/true_mothers","year":"(2020)","score":"fresh"},"/m/wrong_turn_2021":{"name":"Wrong Turn","href":"/m/wrong_turn_2021","year":"(2021)","score":"fresh"},"/m/miss_marx":{"name":"Miss Marx","href":"/m/miss_marx","year":"(2020)","score":"rotten"},"/m/voices_in_the_wind":{"name":"Kaze no Denwa","href":"/m/voices_in_the_wind","year":"(2020)","score":"fresh"},"/m/in_the_heights_2021":{"name":"In the Heights","href":"/m/in_the_heights_2021","year":"(2021)","score":"fresh"}}