{"/m/joy_ride_2023":{"name":"Joy Ride","href":"/m/joy_ride_2023","year":"(2023)","score":"fresh"},"/m/bottoms":{"name":"Bottoms","href":"/m/bottoms","year":"(2023)","score":"fresh"},"/m/problemista":{"name":"Problemista","href":"/m/problemista","year":"(2023)","score":"fresh"},"/m/evil_dead_rise":{"name":"Evil Dead Rise","href":"/m/evil_dead_rise","year":"(2023)","score":"fresh"},"/m/the_unbearable_weight_of_massive_talent":{"name":"The Unbearable Weight of Massive Talent","href":"/m/the_unbearable_weight_of_massive_talent","year":"(2022)","score":"fresh"},"/m/ant_man_and_the_wasp_quantumania":{"name":"Ant-Man and The Wasp: Quantumania","href":"/m/ant_man_and_the_wasp_quantumania","year":"(2023)","score":"fresh"},"/m/glass_onion_a_knives_out_mystery":{"name":"Glass Onion: A Knives Out Mystery","href":"/m/glass_onion_a_knives_out_mystery","year":"(2022)","score":"fresh"},"/m/everything_everywhere_all_at_once":{"name":"Everything Everywhere All at Once","href":"/m/everything_everywhere_all_at_once","year":"(2022)","score":"fresh"},"/m/the_whale_2022":{"name":"The Whale","href":"/m/the_whale_2022","year":"(2022)","score":"rotten"},"/m/babylon_2022":{"name":"Babylon","href":"/m/babylon_2022","year":"(2022)","score":"fresh"},"/m/missing_2023":{"name":"Missing","href":"/m/missing_2023","year":"(2023)","score":"fresh"},"/m/black_panther_wakanda_forever":{"name":"Black Panther: Wakanda Forever","href":"/m/black_panther_wakanda_forever","year":"(2022)","score":"fresh"},"/m/the_menu":{"name":"The Menu","href":"/m/the_menu","year":"(2022)","score":"fresh"},"/m/smile_2022":{"name":"Smile","href":"/m/smile_2022","year":"(2022)","score":"rotten"},"/m/dont_worry_darling":{"name":"Don't Worry Darling","href":"/m/dont_worry_darling","year":"(2022)","score":"fresh"},"/m/elvis":{"name":"Elvis","href":"/m/elvis","year":"(2022)","score":"fresh"},"/m/the_bobs_burgers_movie":{"name":"The Bob's Burgers Movie","href":"/m/the_bobs_burgers_movie","year":"(2022)","score":"fresh"},"/m/top_gun_maverick":{"name":"Top Gun: Maverick","href":"/m/top_gun_maverick","year":"(2022)","score":"fresh"},"/m/inbetween_girl":{"name":"Inbetween Girl","href":"/m/inbetween_girl","year":"(2021)","score":"fresh"},"/m/doctor_strange_in_the_multiverse_of_madness":{"name":"Doctor Strange in the Multiverse of Madness","href":"/m/doctor_strange_in_the_multiverse_of_madness","year":"(2022)","score":"fresh"},"/m/the_northman":{"name":"The Northman","href":"/m/the_northman","year":"(2022)","score":"fresh"},"/m/bodies_bodies_bodies":{"name":"Bodies Bodies Bodies","href":"/m/bodies_bodies_bodies","year":"(2022)","score":"fresh"},"/m/x_2022":{"name":"X","href":"/m/x_2022","year":"(2022)","score":"fresh"},"/m/after_yang":{"name":"After Yang","href":"/m/after_yang","year":"(2021)","score":"fresh"},"/m/the_batman":{"name":"The Batman","href":"/m/the_batman","year":"(2022)","score":"fresh"},"/m/i_want_you_back":{"name":"I Want You Back","href":"/m/i_want_you_back","year":"(2022)","score":"fresh"},"/m/red_rocket":{"name":"Red Rocket","href":"/m/red_rocket","year":"(2021)","score":"fresh"},"/m/nightmare_alley_2021":{"name":"Nightmare Alley","href":"/m/nightmare_alley_2021","year":"(2021)","score":"fresh"},"/m/spider_man_no_way_home":{"name":"Spider-Man: No Way Home","href":"/m/spider_man_no_way_home","year":"(2021)","score":"fresh"},"/m/west_side_story_2021":{"name":"West Side Story","href":"/m/west_side_story_2021","year":"(2021)","score":"rotten"},"/m/house_of_gucci":{"name":"House of Gucci","href":"/m/house_of_gucci","year":"(2021)","score":"fresh"},"/m/the_humans":{"name":"The Humans","href":"/m/the_humans","year":"(2021)","score":"fresh"},"/m/spencer_2021":{"name":"Spencer","href":"/m/spencer_2021","year":"(2021)","score":"fresh"},"/m/eternals":{"name":"Eternals","href":"/m/eternals","year":"(2021)","score":"fresh"},"/m/cmon_cmon":{"name":"C'mon C'mon","href":"/m/cmon_cmon","year":"(2021)","score":"fresh"},"/m/the_french_dispatch":{"name":"The French Dispatch","href":"/m/the_french_dispatch","year":"(2021)","score":"fresh"},"/m/dune_2021":{"name":"Dune","href":"/m/dune_2021","year":"(2021)","score":"rotten"},"/m/lamb_2021":{"name":"Lamb","href":"/m/lamb_2021","year":"(2021)","score":"fresh"},"/m/titane":{"name":"Titane","href":"/m/titane","year":"(2021)","score":"fresh"},"/m/dear_evan_hansen":{"name":"Dear Evan Hansen","href":"/m/dear_evan_hansen","year":"(2021)","score":"rotten"},"/m/shang_chi_and_the_legend_of_the_ten_rings":{"name":"Shang-Chi and the Legend of the Ten Rings","href":"/m/shang_chi_and_the_legend_of_the_ten_rings","year":"(2021)","score":"fresh"},"/m/the_sparks_brothers":{"name":"The Sparks Brothers","href":"/m/the_sparks_brothers","year":"(2021)","score":"fresh"},"/m/annette":{"name":"Annette","href":"/m/annette","year":"(2021)","score":"rotten"},"/m/the_suicide_squad":{"name":"The Suicide Squad","href":"/m/the_suicide_squad","year":"(2021)","score":"fresh"},"/m/the_green_knight":{"name":"The Green Knight","href":"/m/the_green_knight","year":"(2021)","score":"fresh"},"/m/nine_days":{"name":"Nine Days","href":"/m/nine_days","year":"(2020)","score":"fresh"},"/m/i_carry_you_with_me":{"name":"I Carry You With Me","href":"/m/i_carry_you_with_me","year":"(2020)","score":"fresh"},"/m/black_widow_2021":{"name":"Black Widow","href":"/m/black_widow_2021","year":"(2021)","score":"fresh"},"/m/zola":{"name":"Zola","href":"/m/zola","year":"(2020)","score":"fresh"},"/m/luca_2021":{"name":"Luca","href":"/m/luca_2021","year":"(2021)","score":"fresh"}}