{"/m/meet_me_in_st_louis":{"name":"Meet Me in St. Louis","href":"/m/meet_me_in_st_louis","year":"(1944)","score":"fresh"},"/m/hellbender":{"name":"Hellbender","href":"/m/hellbender","year":"(2021)","score":"fresh"},"/m/dead_and_beautiful":{"name":"Dead & Beautiful","href":"/m/dead_and_beautiful","year":"(2021)","score":"rotten"},"/m/i_trapped_the_devil":{"name":"I Trapped the Devil","href":"/m/i_trapped_the_devil","year":"(2019)","score":"rotten"},"/m/lady_boss_the_jackie_collins_story":{"name":"Lady Boss: The Jackie Collins Story","href":"/m/lady_boss_the_jackie_collins_story","year":"(2021)","score":"fresh"},"/m/the_amusement_park":{"name":"The Amusement Park","href":"/m/the_amusement_park","year":"(1973)","score":"rotten"},"/m/friends_the_reunion":{"name":"Friends: The Reunion","href":"/m/friends_the_reunion","year":"(2021)","score":"fresh"},"/m/lucy_the_human_chimp":{"name":"Lucy the Human Chimp","href":"/m/lucy_the_human_chimp","year":"(2021)","score":"fresh"},"/m/tina":{"name":"Tina","href":"/m/tina","year":"(2021)","score":"fresh"},"/m/the_united_states_vs_billie_holiday":{"name":"The United States vs. Billie Holiday","href":"/m/the_united_states_vs_billie_holiday","year":"(2021)","score":"rotten"},"/m/2f687d21-dce1-3483-bbd9-9efce374acfc":{"name":"Effigy: Poison and the City","href":"/m/2f687d21-dce1-3483-bbd9-9efce374acfc","year":"(2019)","score":"fresh"},"/m/my_psychedelic_love_story":{"name":"My Psychedelic Love Story","href":"/m/my_psychedelic_love_story","year":"(2020)","score":"fresh"},"/m/exhumed_a_history_of_zombies":{"name":"Exhumed: A History of Zombies","href":"/m/exhumed_a_history_of_zombies","year":"(2020)","score":"rotten"},"/m/books_of_blood":{"name":"Books of Blood","href":"/m/books_of_blood","year":"(2020)","score":"fresh"},"/m/all_the_way_2016":{"name":"All the Way","href":"/m/all_the_way_2016","year":"(2016)","score":"rotten"},"/m/centigrade_2020":{"name":"Centigrade","href":"/m/centigrade_2020","year":"(2020)","score":"rotten"},"/m/the_binge":{"name":"The Binge","href":"/m/the_binge","year":"(2020)","score":"rotten"},"/m/the_sleepover":{"name":"The Sleepover","href":"/m/the_sleepover","year":"(2020)","score":"fresh"},"/m/mr_jones_2019":{"name":"Mr. Jones","href":"/m/mr_jones_2019","year":"(2019)","score":"fresh"},"/m/the_vast_of_night":{"name":"The Vast of Night","href":"/m/the_vast_of_night","year":"(2019)","score":"fresh"},"/m/the_wretched_2020":{"name":"The Wretched","href":"/m/the_wretched_2020","year":"(2019)","score":"rotten"},"/m/the_apollo":{"name":"The Apollo","href":"/m/the_apollo","year":"(2019)","score":"fresh"},"/m/untouchable_2019":{"name":"Untouchable","href":"/m/untouchable_2019","year":"(2019)","score":"fresh"},"/m/hitsville_the_making_of_motown":{"name":"Hitsville: The Making of Motown","href":"/m/hitsville_the_making_of_motown","year":"(2019)","score":"fresh"},"/m/zombie_tidal_wave":{"name":"Zombie Tidal Wave","href":"/m/zombie_tidal_wave","year":"(2019)","score":"fresh"},"/m/woodstock_three_days_that_defined_a_generation":{"name":"Woodstock: Three Days That Defined a Generation","href":"/m/woodstock_three_days_that_defined_a_generation","year":"(2019)","score":"rotten"},"/m/share_2019":{"name":"Share","href":"/m/share_2019","year":"(2019)","score":"rotten"},"/m/deadwood_the_movie":{"name":"Deadwood: The Movie","href":"/m/deadwood_the_movie","year":"(2019)","score":"fresh"},"/m/the_highwaymen":{"name":"The Highwaymen","href":"/m/the_highwaymen","year":"(2019)","score":"fresh"},"/m/the_truth_about_killer_robots":{"name":"The Truth About Killer Robots","href":"/m/the_truth_about_killer_robots","year":"(2018)","score":"rotten"},"/m/sugar_town_2018":{"name":"Sugar Town","href":"/m/sugar_town_2018","year":"(2018)","score":"fresh"},"/m/going_to_war":{"name":"Going to War","href":"/m/going_to_war","year":"(2018)","score":"fresh"},"/m/served_like_a_girl":{"name":"Served Like a Girl","href":"/m/served_like_a_girl","year":"(2017)","score":"fresh"},"/m/the_final_year":{"name":"The Final Year","href":"/m/the_final_year","year":"(2017)","score":"rotten"},"/m/tiny_shoulders_rethinking_barbie":{"name":"Tiny Shoulders: Rethinking Barbie","href":"/m/tiny_shoulders_rethinking_barbie","year":"(2018)","score":"fresh"},"/m/elvis_presley_the_searcher":{"name":"Elvis Presley: The Searcher","href":"/m/elvis_presley_the_searcher","year":"(2018)","score":"fresh"},"/m/operation_odessa":{"name":"Operation Odessa","href":"/m/operation_odessa","year":"(2018)","score":"fresh"},"/m/arthur_miller_writer":{"name":"Arthur Miller: Writer","href":"/m/arthur_miller_writer","year":"(2017)","score":"rotten"},"/m/final_vision":{"name":"Final Vision","href":"/m/final_vision","year":"(2017)","score":"rotten"},"/m/it_2017":{"name":"It","href":"/m/it_2017","year":"(2017)","score":"fresh"},"/m/the_wizard_of_lies":{"name":"The Wizard of Lies","href":"/m/the_wizard_of_lies","year":"(2017)","score":"rotten"},"/m/the_prison_in_twelve_landscapes":{"name":"The Prison in Twelve Landscapes","href":"/m/the_prison_in_twelve_landscapes","year":"(2016)","score":"fresh"},"/m/disgraced_2017":{"name":"Disgraced","href":"/m/disgraced_2017","year":"(2017)","score":"fresh"},"/m/deidra_and_laney_rob_a_train":{"name":"Deidra & Laney Rob a Train","href":"/m/deidra_and_laney_rob_a_train","year":"(2017)","score":"fresh"},"/m/tallulah":{"name":"Tallulah","href":"/m/tallulah","year":"(2016)","score":"fresh"},"/m/an_unreal_dream_the_michael_morton_story":{"name":"An Unreal Dream: The Michael Morton Story","href":"/m/an_unreal_dream_the_michael_morton_story","year":"(2013)","score":"fresh"},"/m/paradise-a-trilogy-of-hope":{"name":"Paradise: A Trilogy of Hope","href":"/m/paradise-a-trilogy-of-hope","year":"(2013)","score":"fresh"},"/m/our_nixon":{"name":"Our Nixon","href":"/m/our_nixon","year":"(2013)","score":"fresh"}}