{"/m/il_sol_dellavvenire":{"name":"A Brighter Tomorrow","href":"/m/il_sol_dellavvenire","year":"(2023)","score":"fresh"},"/m/the_eight_mountains":{"name":"The Eight Mountains","href":"/m/the_eight_mountains","year":"(2022)","score":"fresh"},"/m/the_girls_are_alright":{"name":"The Girls Are Alright","href":"/m/the_girls_are_alright","year":"(2023)","score":"fresh"},"/m/the_eternal_daughter":{"name":"The Eternal Daughter","href":"/m/the_eternal_daughter","year":"(2022)","score":"fresh"},"/m/godland":{"name":"Godland","href":"/m/godland","year":"(2022)","score":"fresh"},"/m/the_adventures_of_gigi_the_law":{"name":"The Adventures of Gigi the Law","href":"/m/the_adventures_of_gigi_the_law","year":"(2022)","score":"fresh"},"/m/medusa_deluxe":{"name":"Medusa Deluxe","href":"/m/medusa_deluxe","year":"(2022)","score":"fresh"},"/m/sparta":{"name":"Sparta","href":"/m/sparta","year":"(2022)","score":"fresh"},"/m/rimini":{"name":"Rimini","href":"/m/rimini","year":"(2022)","score":"fresh"},"/m/narrow_path_to_happiness":{"name":"Narrow Path to Happiness","href":"/m/narrow_path_to_happiness","year":"(2023)","score":"fresh"},"/m/all_the_beauty_and_the_bloodshed":{"name":"All the Beauty and the Bloodshed","href":"/m/all_the_beauty_and_the_bloodshed","year":"(2022)","score":"fresh"},"/m/the_unlikely_pilgrimage_of_harold_fry":{"name":"Unlikely Pilgrimage Of Harold Fry, The","href":"/m/the_unlikely_pilgrimage_of_harold_fry","year":"(2023)","score":"fresh"},"/m/no_bears":{"name":"No Bears","href":"/m/no_bears","year":"(2022)","score":"fresh"},"/m/the_crime_is_mine":{"name":"The Crime Is Mine","href":"/m/the_crime_is_mine","year":"(2023)","score":"fresh"},"/m/the_march_on_rome":{"name":"The March on Rome","href":"/m/the_march_on_rome","year":"(2022)","score":"fresh"},"/m/anhell69":{"name":"Anhell69","href":"/m/anhell69","year":"(2022)","score":"fresh"},"/m/cork":{"name":"Cork","href":"/m/cork","year":"(2022)","score":"fresh"},"/m/news_from_home":{"name":"News From Home","href":"/m/news_from_home","year":"(1977)","score":"fresh"},"/m/sonne":{"name":"Sonne","href":"/m/sonne","year":"(2022)","score":"fresh"},"/m/saint_omer":{"name":"Saint Omer","href":"/m/saint_omer","year":"(2022)","score":"fresh"},"/m/the_water_2022":{"name":"The Water","href":"/m/the_water_2022","year":"(2022)","score":"fresh"},"/m/tar_2022":{"name":"Tár","href":"/m/tar_2022","year":"(2022)","score":"fresh"},"/m/las_gentiles":{"name":"Las Gentiles","href":"/m/las_gentiles","year":"(2021)","score":"fresh"},"/m/gabi_between_ages_8_and_13":{"name":"Gabi, Between Ages 8 and 13","href":"/m/gabi_between_ages_8_and_13","year":"(2021)","score":"fresh"},"/m/seire":{"name":"Seire","href":"/m/seire","year":"(2021)","score":"fresh"},"/m/hypochondriac":{"name":"Hypochondriac","href":"/m/hypochondriac","year":"(2022)","score":"fresh"},"/m/saloum":{"name":"Saloum","href":"/m/saloum","year":"(2021)","score":"fresh"},"/m/perfect_blue_1999":{"name":"Perfect Blue","href":"/m/perfect_blue_1999","year":"(1997)","score":"fresh"},"/m/piggy_2022":{"name":"Piggy","href":"/m/piggy_2022","year":"(2022)","score":"fresh"},"/m/wild_flowers_2022":{"name":"Wild Flowers","href":"/m/wild_flowers_2022","year":"(2022)","score":"fresh"},"/m/unicorn_wars":{"name":"Unicorn Wars","href":"/m/unicorn_wars","year":"(2022)","score":"fresh"},"/m/argentina_1985":{"name":"Argentina, 1985","href":"/m/argentina_1985","year":"(2022)","score":"fresh"},"/m/crimes_of_the_future_2022":{"name":"Crimes of the Future","href":"/m/crimes_of_the_future_2022","year":"(2022)","score":"fresh"},"/m/the_handmaiden":{"name":"The Handmaiden","href":"/m/the_handmaiden","year":"(2016)","score":"fresh"},"/m/pacifiction":{"name":"Pacifiction","href":"/m/pacifiction","year":"(2022)","score":"fresh"},"/m/into_my_name":{"name":"Into My Name","href":"/m/into_my_name","year":"(2022)","score":"fresh"},"/m/she_will":{"name":"She Will","href":"/m/she_will","year":"(2021)","score":"fresh"},"/m/vortex_2021":{"name":"Vortex","href":"/m/vortex_2021","year":"(2021)","score":"fresh"},"/m/una_femmina_the_code_of_silence":{"name":"Una Femmina - The Code of Silence","href":"/m/una_femmina_the_code_of_silence","year":"(2022)","score":"fresh"},"/m/undergods":{"name":"Undergods","href":"/m/undergods","year":"(2020)","score":"fresh"},"/m/nudo_mixteco":{"name":"Nudo mixteco","href":"/m/nudo_mixteco","year":"(2020)","score":"fresh"},"/m/myanmar_diaries":{"name":"Myanmar Diaries","href":"/m/myanmar_diaries","year":"(2022)","score":"fresh"},"/m/my_emptiness_and_i":{"name":"My Emptiness and I","href":"/m/my_emptiness_and_i","year":"(2022)","score":"fresh"},"/m/atlantide":{"name":"Atlantide","href":"/m/atlantide","year":"(2021)","score":"fresh"},"/m/eugenie_grandet":{"name":"Eugénie Grandet","href":"/m/eugenie_grandet","year":"(2021)","score":"fresh"},"/m/the_electrical_life_of_louis_wain":{"name":"The Electrical Life of Louis Wain","href":"/m/the_electrical_life_of_louis_wain","year":"(2021)","score":"fresh"},"/m/azor":{"name":"Azor","href":"/m/azor","year":"(2021)","score":"fresh"},"/m/palombella_rossa":{"name":"Palombella rossa","href":"/m/palombella_rossa","year":"(1989)","score":"fresh"},"/m/the_inner_cage":{"name":"The Inner Cage","href":"/m/the_inner_cage","year":"(2021)","score":"fresh"},"/m/a_chiara":{"name":"A Chiara","href":"/m/a_chiara","year":"(2021)","score":"fresh"}}