{"/m/eldorado_everything_the_nazis_hate":{"name":"Eldorado: Everything the Nazis Hate","href":"/m/eldorado_everything_the_nazis_hate","year":"(2023)","score":"rotten"},"/m/tetris":{"name":"Tetris","href":"/m/tetris","year":"(2023)","score":"fresh"},"/m/finding_michael":{"name":"Finding Michael","href":"/m/finding_michael","year":"(2023)","score":"fresh"},"/m/chris_rock_selective_outrage":{"name":"Chris Rock: Selective Outrage","href":"/m/chris_rock_selective_outrage","year":"(2023)","score":"fresh"},"/m/the_fire_within_a_requiem_for_katia_and_maurice_krafft":{"name":"The Fire Within: A Requiem for Katia and Maurice Krafft","href":"/m/the_fire_within_a_requiem_for_katia_and_maurice_krafft","year":"(2022)","score":"fresh"},"/m/thirteen_lives":{"name":"Thirteen Lives","href":"/m/thirteen_lives","year":"(2022)","score":"fresh"},"/m/bo_burnham_inside":{"name":"Bo Burnham: Inside","href":"/m/bo_burnham_inside","year":"(2021)","score":"rotten"}}