{"/m/barbie":{"name":"Barbie","href":"/m/barbie","year":"(2023)","score":"fresh"},"/m/the_flash_2023":{"name":"The Flash","href":"/m/the_flash_2023","year":"(2023)","score":"fresh"},"/m/the_little_mermaid_2023":{"name":"The Little Mermaid","href":"/m/the_little_mermaid_2023","year":"(2023)","score":"fresh"},"/m/fast_x":{"name":"Fast X","href":"/m/fast_x","year":"(2023)","score":"fresh"},"/m/guardians_of_the_galaxy_vol_3":{"name":"Guardians of the Galaxy Vol. 3","href":"/m/guardians_of_the_galaxy_vol_3","year":"(2023)","score":"fresh"},"/m/shazam_fury_of_the_gods":{"name":"Shazam! Fury of the Gods","href":"/m/shazam_fury_of_the_gods","year":"(2023)","score":"fresh"},"/m/black_panther_wakanda_forever":{"name":"Black Panther: Wakanda Forever","href":"/m/black_panther_wakanda_forever","year":"(2022)","score":"fresh"},"/m/black_adam":{"name":"Black Adam","href":"/m/black_adam","year":"(2022)","score":"rotten"},"/m/pinocchio_2022":{"name":"Pinocchio","href":"/m/pinocchio_2022","year":"(2022)","score":"rotten"},"/m/thor_love_and_thunder":{"name":"Thor: Love and Thunder","href":"/m/thor_love_and_thunder","year":"(2022)","score":"fresh"},"/m/lightyear":{"name":"Lightyear","href":"/m/lightyear","year":"(2022)","score":"fresh"},"/m/jurassic_world_dominion":{"name":"Jurassic World Dominion","href":"/m/jurassic_world_dominion","year":"(2022)","score":"fresh"},"/m/the_bobs_burgers_movie":{"name":"The Bob's Burgers Movie","href":"/m/the_bobs_burgers_movie","year":"(2022)","score":"fresh"},"/m/doctor_strange_in_the_multiverse_of_madness":{"name":"Doctor Strange in the Multiverse of Madness","href":"/m/doctor_strange_in_the_multiverse_of_madness","year":"(2022)","score":"fresh"},"/m/fantastic_beasts_the_secrets_of_dumbledore":{"name":"Fantastic Beasts: The Secrets of Dumbledore","href":"/m/fantastic_beasts_the_secrets_of_dumbledore","year":"(2022)","score":"fresh"},"/m/the_batman":{"name":"The Batman","href":"/m/the_batman","year":"(2022)","score":"fresh"},"/m/uncharted_2022":{"name":"Uncharted","href":"/m/uncharted_2022","year":"(2022)","score":"fresh"},"/m/captain_america_the_winter_soldier_2014":{"name":"Captain America: The Winter Soldier","href":"/m/captain_america_the_winter_soldier_2014","year":"(2014)","score":"fresh"},"/m/the_last_duel_2021":{"name":"The Last Duel","href":"/m/the_last_duel_2021","year":"(2021)","score":"fresh"},"/m/the_matrix_resurrections":{"name":"The Matrix Resurrections","href":"/m/the_matrix_resurrections","year":"(2021)","score":"fresh"},"/m/spider_man_no_way_home":{"name":"Spider-Man: No Way Home","href":"/m/spider_man_no_way_home","year":"(2021)","score":"fresh"},"/m/west_side_story_2021":{"name":"West Side Story","href":"/m/west_side_story_2021","year":"(2021)","score":"fresh"},"/m/encanto_2021":{"name":"Encanto","href":"/m/encanto_2021","year":"(2021)","score":"fresh"},"/m/eternals":{"name":"Eternals","href":"/m/eternals","year":"(2021)","score":"rotten"},"/m/free_guy":{"name":"Free Guy","href":"/m/free_guy","year":"(2021)","score":"fresh"},"/m/the_suicide_squad":{"name":"The Suicide Squad","href":"/m/the_suicide_squad","year":"(2021)","score":"fresh"},"/m/black_widow_2021":{"name":"Black Widow","href":"/m/black_widow_2021","year":"(2021)","score":"fresh"},"/m/soul":{"name":"Soul","href":"/m/soul","year":"(2020)","score":"rotten"},"/m/f9":{"name":"F9 The Fast Saga","href":"/m/f9","year":"(2021)","score":"fresh"},"/m/cruella":{"name":"Cruella","href":"/m/cruella","year":"(2021)","score":"fresh"},"/m/army_of_the_dead_2021":{"name":"Army Of The Dead","href":"/m/army_of_the_dead_2021","year":"(2021)","score":"fresh"},"/m/zack_snyders_justice_league":{"name":"Zack Snyder's Justice League","href":"/m/zack_snyders_justice_league","year":"(2021)","score":"fresh"},"/m/over_the_moon_2020":{"name":"Over the Moon","href":"/m/over_the_moon_2020","year":"(2020)","score":"fresh"},"/m/mulan_2020":{"name":"Mulan","href":"/m/mulan_2020","year":"(2020)","score":"fresh"},"/m/artemis_fowl":{"name":"Artemis Fowl","href":"/m/artemis_fowl","year":"(2020)","score":"rotten"},"/m/onward":{"name":"Onward","href":"/m/onward","year":"(2020)","score":"fresh"},"/m/birds_of_prey_2020":{"name":"Birds of Prey (and the Fantabulous Emancipation of One Harley Quinn)","href":"/m/birds_of_prey_2020","year":"(2020)","score":"fresh"},"/m/dolittle":{"name":"Dolittle","href":"/m/dolittle","year":"(2020)","score":"rotten"},"/m/star_wars_the_rise_of_skywalker":{"name":"Star Wars: The Rise of Skywalker","href":"/m/star_wars_the_rise_of_skywalker","year":"(2019)","score":"fresh"},"/m/queen_and_slim":{"name":"Queen & Slim","href":"/m/queen_and_slim","year":"(2019)","score":"fresh"},"/m/guardians_of_the_galaxy":{"name":"Guardians of the Galaxy","href":"/m/guardians_of_the_galaxy","year":"(2014)","score":"fresh"},"/m/knives_out":{"name":"Knives Out","href":"/m/knives_out","year":"(2019)","score":"fresh"},"/m/noelle_2019":{"name":"Noelle","href":"/m/noelle_2019","year":"(2019)","score":"rotten"},"/m/klaus":{"name":"Klaus","href":"/m/klaus","year":"(2019)","score":"fresh"},"/m/ford_v_ferrari":{"name":"Ford v Ferrari","href":"/m/ford_v_ferrari","year":"(2019)","score":"fresh"},"/m/lady_and_the_tramp_2019":{"name":"Lady and the Tramp","href":"/m/lady_and_the_tramp_2019","year":"(2019)","score":"fresh"},"/m/doctor_sleep":{"name":"Doctor Sleep","href":"/m/doctor_sleep","year":"(2019)","score":"rotten"},"/m/interstellar_2014":{"name":"Interstellar","href":"/m/interstellar_2014","year":"(2014)","score":"fresh"},"/m/gravity_2013":{"name":"Gravity","href":"/m/gravity_2013","year":"(2013)","score":"fresh"},"/m/the_martian":{"name":"The Martian","href":"/m/the_martian","year":"(2015)","score":"fresh"}}