{"/m/master_gardener":{"name":"Master Gardener","href":"/m/master_gardener","year":"(2022)","score":"fresh"},"/m/kiss_the_future":{"name":"Kiss the Future","href":"/m/kiss_the_future","year":"(2023)","score":"fresh"},"/m/corsage":{"name":"Corsage","href":"/m/corsage","year":"(2022)","score":"fresh"},"/m/the_swimmers_2022":{"name":"The Swimmers","href":"/m/the_swimmers_2022","year":"(2022)","score":"fresh"},"/m/moonage_daydream":{"name":"Moonage Daydream","href":"/m/moonage_daydream","year":"(2022)","score":"fresh"},"/m/armageddon_time":{"name":"Armageddon Time","href":"/m/armageddon_time","year":"(2022)","score":"fresh"},"/m/against_the_ice":{"name":"Against the Ice","href":"/m/against_the_ice","year":"(2022)","score":"rotten"},"/m/flux_gourmet":{"name":"Flux Gourmet","href":"/m/flux_gourmet","year":"(2022)","score":"fresh"},"/m/the_outfit_2022":{"name":"The Outfit","href":"/m/the_outfit_2022","year":"(2022)","score":"fresh"},"/m/resurrection_2022":{"name":"Resurrection","href":"/m/resurrection_2022","year":"(2022)","score":"fresh"},"/m/only_the_animals":{"name":"Only the Animals","href":"/m/only_the_animals","year":"(2019)","score":"fresh"},"/m/bull_2022":{"name":"Bull","href":"/m/bull_2022","year":"(2021)","score":"fresh"},"/m/oasis_knebworth_1996":{"name":"Oasis Knebworth 1996","href":"/m/oasis_knebworth_1996","year":"(2021)","score":"fresh"},"/m/enforcement":{"name":"Enforcement","href":"/m/enforcement","year":"(2020)","score":"fresh"},"/m/candyman_2021":{"name":"Candyman","href":"/m/candyman_2021","year":"(2021)","score":"fresh"},"/m/jungle_cruise":{"name":"Jungle Cruise","href":"/m/jungle_cruise","year":"(2021)","score":"fresh"},"/m/in_the_earth":{"name":"In The Earth","href":"/m/in_the_earth","year":"(2021)","score":"fresh"},"/m/ghosts_of_war":{"name":"Ghosts of War","href":"/m/ghosts_of_war","year":"(2020)","score":"rotten"},"/m/7500":{"name":"7500","href":"/m/7500","year":"(2019)","score":"fresh"},"/m/the_traitor_2020":{"name":"The Traitor","href":"/m/the_traitor_2020","year":"(2019)","score":"fresh"},"/m/unhinged_2020":{"name":"Unhinged","href":"/m/unhinged_2020","year":"(2020)","score":"fresh"},"/m/proxima_2019":{"name":"Proxima","href":"/m/proxima_2019","year":"(2019)","score":"fresh"},"/m/matthias_and_maxime":{"name":"Matthias & Maxime","href":"/m/matthias_and_maxime","year":"(2019)","score":"fresh"},"/m/the_other_lamb":{"name":"The Other Lamb","href":"/m/the_other_lamb","year":"(2019)","score":"fresh"},"/m/kajillionaire":{"name":"Kajillionaire","href":"/m/kajillionaire","year":"(2020)","score":"fresh"},"/m/relic":{"name":"Relic","href":"/m/relic","year":"(2020)","score":"fresh"},"/m/here_are_the_young_men":{"name":"Here Are the Young Men","href":"/m/here_are_the_young_men","year":"(2021)","score":"fresh"},"/m/the_sparks_brothers":{"name":"The Sparks Brothers","href":"/m/the_sparks_brothers","year":"(2021)","score":"fresh"},"/m/im_thinking_of_ending_things":{"name":"I'm Thinking of Ending Things","href":"/m/im_thinking_of_ending_things","year":"(2020)","score":"fresh"},"/m/sulphur_and_white":{"name":"Sulphur and White","href":"/m/sulphur_and_white","year":"(2019)","score":"fresh"},"/m/mogul_mowgli":{"name":"Mogul Mowgli","href":"/m/mogul_mowgli","year":"(2020)","score":"fresh"},"/m/nobody_2021":{"name":"Nobody","href":"/m/nobody_2021","year":"(2021)","score":"fresh"},"/m/dinner_in_america":{"name":"Dinner in America","href":"/m/dinner_in_america","year":"(2020)","score":"fresh"},"/m/the_vigil_2021":{"name":"The Vigil","href":"/m/the_vigil_2021","year":"(2019)","score":"fresh"},"/m/mank":{"name":"Mank","href":"/m/mank","year":"(2020)","score":"fresh"},"/m/ted_k":{"name":"Ted K","href":"/m/ted_k","year":"(2021)","score":"fresh"},"/m/savage_2019_2":{"name":"Savage","href":"/m/savage_2019_2","year":"(2019)","score":"fresh"},"/m/time_to_hunt":{"name":"Time to Hunt","href":"/m/time_to_hunt","year":"(2020)","score":"fresh"},"/m/my_salinger_year":{"name":"My Salinger Year","href":"/m/my_salinger_year","year":"(2020)","score":"fresh"},"/m/the_personal_history_of_david_copperfield":{"name":"The Personal History of David Copperfield","href":"/m/the_personal_history_of_david_copperfield","year":"(2019)","score":"fresh"},"/m/parasite_2019":{"name":"Parasite","href":"/m/parasite_2019","year":"(2019)","score":"fresh"},"/m/the_irishman":{"name":"The Irishman","href":"/m/the_irishman","year":"(2019)","score":"fresh"},"/m/meeting_gorbachev":{"name":"Meeting Gorbachev","href":"/m/meeting_gorbachev","year":"(2018)","score":"fresh"},"/m/monos":{"name":"Monos","href":"/m/monos","year":"(2019)","score":"fresh"},"/m/it_chapter_two":{"name":"It: Chapter Two","href":"/m/it_chapter_two","year":"(2019)","score":"fresh"},"/m/once_upon_a_time_in_hollywood":{"name":"Once Upon a Time... In Hollywood","href":"/m/once_upon_a_time_in_hollywood","year":"(2019)","score":"fresh"},"/m/the_dead_dont_die_2019":{"name":"The Dead Don't Die","href":"/m/the_dead_dont_die_2019","year":"(2019)","score":"fresh"},"/m/childs_play_2019":{"name":"Child's Play","href":"/m/childs_play_2019","year":"(2019)","score":"fresh"},"/m/liam_gallagher_as_it_was":{"name":"Liam Gallagher: As It Was","href":"/m/liam_gallagher_as_it_was","year":"(2019)","score":"fresh"},"/m/godzilla_king_of_the_monsters_2019":{"name":"Godzilla: King of the Monsters","href":"/m/godzilla_king_of_the_monsters_2019","year":"(2019)","score":"fresh"}}