{"/m/a_haunting_in_venice":{"name":"A Haunting in Venice","href":"/m/a_haunting_in_venice","year":"(2023)","score":"fresh"},"/m/the_nun_ii":{"name":"The Nun II","href":"/m/the_nun_ii","year":"(2023)","score":"rotten"},"/m/brightwood":{"name":"Brightwood","href":"/m/brightwood","year":"(2022)","score":"fresh"},"/m/the_last_voyage_of_the_demeter":{"name":"The Last Voyage of the Demeter","href":"/m/the_last_voyage_of_the_demeter","year":"(2023)","score":"fresh"},"/m/new_life_2023":{"name":"New Life","href":"/m/new_life_2023","year":"(2023)","score":"fresh"},"/m/meg_2_the_trench":{"name":"Meg 2: The Trench","href":"/m/meg_2_the_trench","year":"(2023)","score":"rotten"},"/m/late_night_with_the_devil":{"name":"Late Night With the Devil","href":"/m/late_night_with_the_devil","year":"(2023)","score":"fresh"},"/m/where_the_devil_roams":{"name":"Where the Devil Roams","href":"/m/where_the_devil_roams","year":"(2023)","score":"fresh"},"/m/in_my_mothers_skin":{"name":"In My Mother's Skin","href":"/m/in_my_mothers_skin","year":"(2023)","score":"fresh"},"/m/raging_grace":{"name":"Raging Grace","href":"/m/raging_grace","year":"(2023)","score":"fresh"},"/m/youll_never_find_me":{"name":"You'll Never Find Me","href":"/m/youll_never_find_me","year":"(2023)","score":"fresh"},"/m/the_blackening":{"name":"The Blackening","href":"/m/the_blackening","year":"(2022)","score":"fresh"},"/m/suitable_flesh":{"name":"Suitable Flesh","href":"/m/suitable_flesh","year":"(2023)","score":"fresh"},"/m/the_popes_exorcist":{"name":"The Pope's Exorcist","href":"/m/the_popes_exorcist","year":"(2023)","score":"rotten"},"/m/evil_dead_rise":{"name":"Evil Dead Rise","href":"/m/evil_dead_rise","year":"(2023)","score":"fresh"},"/m/65":{"name":"65","href":"/m/65","year":"(2023)","score":"fresh"},"/m/scream_vi":{"name":"Scream VI","href":"/m/scream_vi","year":"(2023)","score":"fresh"},"/m/unseen_2023":{"name":"Unseen","href":"/m/unseen_2023","year":"(2023)","score":"fresh"},"/m/cocaine_bear":{"name":"Cocaine Bear","href":"/m/cocaine_bear","year":"(2023)","score":"fresh"},"/m/winnie_the_pooh_blood_and_honey":{"name":"Winnie-the-Pooh: Blood and Honey","href":"/m/winnie_the_pooh_blood_and_honey","year":"(2023)","score":"rotten"},"/m/project_wolf_hunting":{"name":"Project Wolf Hunting","href":"/m/project_wolf_hunting","year":"(2022)","score":"rotten"},"/m/she_came_from_the_woods":{"name":"She Came from the Woods","href":"/m/she_came_from_the_woods","year":"(2022)","score":"fresh"},"/m/knock_at_the_cabin":{"name":"Knock at the Cabin","href":"/m/knock_at_the_cabin","year":"(2023)","score":"fresh"},"/m/fear_2023":{"name":"Fear","href":"/m/fear_2023","year":"(2023)","score":"rotten"},"/m/infinity_pool_2023":{"name":"Infinity Pool","href":"/m/infinity_pool_2023","year":"(2023)","score":"fresh"},"/m/skinamarink":{"name":"Skinamarink","href":"/m/skinamarink","year":"(2022)","score":"fresh"},"/m/m3gan":{"name":"M3GAN","href":"/m/m3gan","year":"(2022)","score":"fresh"},"/m/troll_2022":{"name":"Troll","href":"/m/troll_2022","year":"(2022)","score":"fresh"},"/m/terror_train_2022":{"name":"Terror Train","href":"/m/terror_train_2022","year":"(2022)","score":"rotten"},"/m/slashback":{"name":"Slash/Back","href":"/m/slashback","year":"(2022)","score":"fresh"},"/m/christmas_bloody_christmas":{"name":"Christmas Bloody Christmas","href":"/m/christmas_bloody_christmas","year":"(2022)","score":"fresh"},"/m/the_possession_of_hannah_grace":{"name":"The Possession of Hannah Grace","href":"/m/the_possession_of_hannah_grace","year":"(2018)","score":"fresh"},"/m/salems_lot_2004":{"name":"Salem's Lot","href":"/m/salems_lot_2004","year":"(2004)","score":"fresh"},"/m/halloween_ends":{"name":"Halloween Ends","href":"/m/halloween_ends","year":"(2022)","score":"rotten"},"/m/terrifier_2":{"name":"Terrifier 2","href":"/m/terrifier_2","year":"(2022)","score":"fresh"},"/m/jeepers_creepers_reborn":{"name":"Jeepers Creepers: Reborn","href":"/m/jeepers_creepers_reborn","year":"(2022)","score":"rotten"},"/m/my_best_friends_exorcism":{"name":"My Best Friend's Exorcism","href":"/m/my_best_friends_exorcism","year":"(2022)","score":"fresh"},"/m/smile_2022":{"name":"Smile","href":"/m/smile_2022","year":"(2022)","score":"fresh"},"/m/dont_worry_darling":{"name":"Don't Worry Darling","href":"/m/dont_worry_darling","year":"(2022)","score":"fresh"},"/m/goodnight_mommy_2022":{"name":"Goodnight Mommy","href":"/m/goodnight_mommy_2022","year":"(2022)","score":"rotten"},"/m/pearl_2022":{"name":"Pearl","href":"/m/pearl_2022","year":"(2022)","score":"fresh"},"/m/house_of_darkness_2022":{"name":"House of Darkness","href":"/m/house_of_darkness_2022","year":"(2022)","score":"rotten"},"/m/barbarian_2022":{"name":"Barbarian","href":"/m/barbarian_2022","year":"(2022)","score":"fresh"},"/m/beast_2022":{"name":"Beast","href":"/m/beast_2022","year":"(2022)","score":"fresh"},"/m/fall":{"name":"Fall","href":"/m/fall","year":"(2022)","score":"fresh"},"/m/speak_no_evil_2022":{"name":"Speak No Evil","href":"/m/speak_no_evil_2022","year":"(2022)","score":"fresh"},"/m/bodies_bodies_bodies":{"name":"Bodies Bodies Bodies","href":"/m/bodies_bodies_bodies","year":"(2022)","score":"fresh"},"/m/resurrection_2022":{"name":"Resurrection","href":"/m/resurrection_2022","year":"(2022)","score":"fresh"},"/m/the_harbinger_2022":{"name":"The Harbinger","href":"/m/the_harbinger_2022","year":"(2022)","score":"fresh"},"/m/final_cut_2022":{"name":"Final Cut","href":"/m/final_cut_2022","year":"(2022)","score":"fresh"}}