{"/m/legua":{"name":"Légua","href":"/m/legua","year":"(2023)","score":"fresh"},"/m/totem_2023":{"name":"Tótem","href":"/m/totem_2023","year":"(2023)","score":"fresh"},"/m/dont_worry_darling":{"name":"Don't Worry Darling","href":"/m/dont_worry_darling","year":"(2022)","score":"fresh"},"/m/halloween_ends":{"name":"Halloween Ends","href":"/m/halloween_ends","year":"(2022)","score":"rotten"},"/m/crimes_of_the_future_2022":{"name":"Crimes of the Future","href":"/m/crimes_of_the_future_2022","year":"(2022)","score":"fresh"},"/m/the_professor_and_the_madman":{"name":"The Professor and the Madman","href":"/m/the_professor_and_the_madman","year":"(2019)","score":"rotten"},"/m/mrs_lowry_and_son":{"name":"Mrs. Lowry & Son","href":"/m/mrs_lowry_and_son","year":"(2019)","score":"rotten"},"/m/little_women_2019":{"name":"Little Women","href":"/m/little_women_2019","year":"(2019)","score":"fresh"},"/m/judy_2019":{"name":"Judy","href":"/m/judy_2019","year":"(2019)","score":"fresh"},"/m/1917_2019":{"name":"1917","href":"/m/1917_2019","year":"(2019)","score":"fresh"},"/m/sound_of_metal":{"name":"Sound of Metal","href":"/m/sound_of_metal","year":"(2019)","score":"fresh"},"/m/long_story_short_2021":{"name":"Long Story Short","href":"/m/long_story_short_2021","year":"(2021)","score":"fresh"},"/m/promising_young_woman":{"name":"Promising Young Woman","href":"/m/promising_young_woman","year":"(2020)","score":"fresh"},"/m/six_minutes_to_midnight":{"name":"Six Minutes to Midnight","href":"/m/six_minutes_to_midnight","year":"(2020)","score":"rotten"},"/m/radioactive":{"name":"Radioactive","href":"/m/radioactive","year":"(2019)","score":"rotten"},"/m/another_round":{"name":"Another Round","href":"/m/another_round","year":"(2020)","score":"fresh"},"/m/judas_and_the_black_messiah":{"name":"Judas and the Black Messiah","href":"/m/judas_and_the_black_messiah","year":"(2021)","score":"fresh"},"/m/crisis_2021":{"name":"Crisis","href":"/m/crisis_2021","year":"(2021)","score":"rotten"},"/m/wrath_of_man":{"name":"Wrath of Man","href":"/m/wrath_of_man","year":"(2021)","score":"fresh"},"/m/black_widow_2021":{"name":"Black Widow","href":"/m/black_widow_2021","year":"(2021)","score":"fresh"},"/m/1074316-scream":{"name":"Scream","href":"/m/1074316-scream","year":"(1996)","score":"fresh"},"/m/coda_2021":{"name":"CODA","href":"/m/coda_2021","year":"(2021)","score":"fresh"},"/m/land_2021":{"name":"Land","href":"/m/land_2021","year":"(2021)","score":"fresh"},"/m/last_night_in_soho":{"name":"Last Night in Soho","href":"/m/last_night_in_soho","year":"(2021)","score":"fresh"},"/m/bullet_train_2022":{"name":"Bullet Train","href":"/m/bullet_train_2022","year":"(2022)","score":"fresh"},"/m/blue_bayou_2021":{"name":"Blue Bayou","href":"/m/blue_bayou_2021","year":"(2021)","score":"fresh"},"/m/licorice_pizza":{"name":"Licorice Pizza","href":"/m/licorice_pizza","year":"(2021)","score":"fresh"},"/m/king_richard":{"name":"King Richard","href":"/m/king_richard","year":"(2021)","score":"fresh"},"/m/the_lost_daughter":{"name":"The Lost Daughter","href":"/m/the_lost_daughter","year":"(2021)","score":"fresh"},"/m/belfast":{"name":"Belfast","href":"/m/belfast","year":"(2021)","score":"fresh"},"/m/cyrano":{"name":"Cyrano","href":"/m/cyrano","year":"(2021)","score":"fresh"},"/m/press_play_2022":{"name":"Press Play","href":"/m/press_play_2022","year":"(2022)","score":"fresh"},"/m/not_okay":{"name":"Not Okay","href":"/m/not_okay","year":"(2022)","score":"fresh"},"/m/the_northman":{"name":"The Northman","href":"/m/the_northman","year":"(2022)","score":"fresh"},"/m/the_kings_man":{"name":"The King's Man","href":"/m/the_kings_man","year":"(2021)","score":"rotten"},"/m/morbius":{"name":"Morbius","href":"/m/morbius","year":"(2022)","score":"rotten"},"/m/best_sellers":{"name":"Best Sellers","href":"/m/best_sellers","year":"(2021)","score":"rotten"},"/m/thor_love_and_thunder":{"name":"Thor: Love and Thunder","href":"/m/thor_love_and_thunder","year":"(2022)","score":"rotten"},"/m/strange_but_true":{"name":"Strange but True","href":"/m/strange_but_true","year":"(2019)","score":"rotten"},"/m/persuasion":{"name":"Persuasion","href":"/m/persuasion","year":"(2022)","score":"rotten"},"/m/enola_holmes":{"name":"Enola Holmes","href":"/m/enola_holmes","year":"(2020)","score":"fresh"},"/m/cobweb_2023_2":{"name":"Cobweb","href":"/m/cobweb_2023_2","year":"(2023)","score":"fresh"},"/m/it_lives_inside_2023":{"name":"It Lives Inside","href":"/m/it_lives_inside_2023","year":"(2023)","score":"fresh"},"/m/blue_beetle":{"name":"Blue Beetle","href":"/m/blue_beetle","year":"(2023)","score":"fresh"},"/m/a_haunting_in_venice":{"name":"A Haunting in Venice","href":"/m/a_haunting_in_venice","year":"(2023)","score":"fresh"},"/m/the_crime_is_mine":{"name":"The Crime Is Mine","href":"/m/the_crime_is_mine","year":"(2023)","score":"fresh"},"/m/el_conde":{"name":"El Conde","href":"/m/el_conde","year":"(2023)","score":"fresh"},"/m/reality_2023":{"name":"Reality","href":"/m/reality_2023","year":"(2023)","score":"fresh"},"/m/the_nun_ii":{"name":"The Nun II","href":"/m/the_nun_ii","year":"(2023)","score":"rotten"},"/m/the_starling_girl":{"name":"The Starling Girl","href":"/m/the_starling_girl","year":"(2023)","score":"fresh"}}