{"/m/youth_spring":{"name":"Youth (Spring)","href":"/m/youth_spring","year":"(2023)","score":"rotten"},"/m/passages_2023":{"name":"Passages","href":"/m/passages_2023","year":"(2023)","score":"rotten"},"/m/the_wandering_earth_ii":{"name":"The Wandering Earth II","href":"/m/the_wandering_earth_ii","year":"(2023)","score":"rotten"},"/m/the_old_town_girls":{"name":"The Old Town Girls","href":"/m/the_old_town_girls","year":"(2020)","score":"rotten"},"/m/septet_the_story_of_hong_kong":{"name":"Septet : The Story of Hong Kong","href":"/m/septet_the_story_of_hong_kong","year":"(2021)","score":"rotten"},"/m/eternal_spring":{"name":"Eternal Spring","href":"/m/eternal_spring","year":"(2022)","score":"rotten"},"/m/return_to_dust":{"name":"Return to Dust","href":"/m/return_to_dust","year":"(2022)","score":"fresh"},"/m/the_banshees_of_inisherin":{"name":"The Banshees of Inisherin","href":"/m/the_banshees_of_inisherin","year":"(2022)","score":"fresh"},"/m/all_the_beauty_and_the_bloodshed":{"name":"All the Beauty and the Bloodshed","href":"/m/all_the_beauty_and_the_bloodshed","year":"(2022)","score":"rotten"},"/m/the_whale_2022":{"name":"The Whale","href":"/m/the_whale_2022","year":"(2022)","score":"rotten"},"/m/sick_2022":{"name":"Sick","href":"/m/sick_2022","year":"(2022)","score":"fresh"},"/m/glass_onion_a_knives_out_mystery":{"name":"Glass Onion: A Knives Out Mystery","href":"/m/glass_onion_a_knives_out_mystery","year":"(2022)","score":"rotten"},"/m/the_hotel_2022":{"name":"The Hotel","href":"/m/the_hotel_2022","year":"(2022)","score":"rotten"},"/m/the_fabelmans":{"name":"The Fabelmans","href":"/m/the_fabelmans","year":"(2022)","score":"fresh"},"/m/no_bears":{"name":"No Bears","href":"/m/no_bears","year":"(2022)","score":"fresh"},"/m/the_exiles_2022":{"name":"The Exiles","href":"/m/the_exiles_2022","year":"(2022)","score":"fresh"},"/m/being_the_ricardos":{"name":"Being the Ricardos","href":"/m/being_the_ricardos","year":"(2021)","score":"fresh"},"/m/try_harder":{"name":"Try Harder!","href":"/m/try_harder","year":"(2021)","score":"rotten"},"/m/ripples_of_life":{"name":"Ripples of Life","href":"/m/ripples_of_life","year":"(2021)","score":"fresh"},"/m/the_boy_from_medellin":{"name":"The Boy From Medellín","href":"/m/the_boy_from_medellin","year":"(2020)","score":"rotten"},"/m/cliff_walkers":{"name":"Cliff Walkers","href":"/m/cliff_walkers","year":"(2021)","score":"fresh"},"/m/black_medusa":{"name":"Black Medusa","href":"/m/black_medusa","year":"(2021)","score":"rotten"},"/m/the_best_is_yet_to_come_2020":{"name":"The Best Is Yet To Come","href":"/m/the_best_is_yet_to_come_2020","year":"(2020)","score":"rotten"},"/m/better_days_2019":{"name":"Better Days","href":"/m/better_days_2019","year":"(2019)","score":"fresh"},"/m/mulan_2020":{"name":"Mulan","href":"/m/mulan_2020","year":"(2020)","score":"rotten"},"/m/saturday_fiction":{"name":"Saturday Fiction","href":"/m/saturday_fiction","year":"(2019)","score":"fresh"},"/m/to_the_ends_of_the_earth_2020":{"name":"To the Ends of the Earth","href":"/m/to_the_ends_of_the_earth_2020","year":"(2019)","score":"fresh"},"/m/the_wild_goose_lake":{"name":"The Wild Goose Lake","href":"/m/the_wild_goose_lake","year":"(2019)","score":"fresh"},"/m/bacurau":{"name":"Bacurau","href":"/m/bacurau","year":"(2019)","score":"fresh"},"/m/atlantics":{"name":"Atlantics","href":"/m/atlantics","year":"(2019)","score":"fresh"},"/m/oh_mercy":{"name":"Oh Mercy! (Roubaix, Une Lumière)","href":"/m/oh_mercy","year":"(2019)","score":"rotten"},"/m/les_miserables_2020":{"name":"Les misérables","href":"/m/les_miserables_2020","year":"(2019)","score":"rotten"},"/m/young_ahmed":{"name":"Young Ahmed","href":"/m/young_ahmed","year":"(2019)","score":"rotten"},"/m/once_upon_a_time_in_hollywood":{"name":"Once Upon a Time... In Hollywood","href":"/m/once_upon_a_time_in_hollywood","year":"(2019)","score":"fresh"},"/m/the_lighthouse_2019":{"name":"The Lighthouse","href":"/m/the_lighthouse_2019","year":"(2019)","score":"fresh"},"/m/a_hidden_life_2019":{"name":"A Hidden Life","href":"/m/a_hidden_life_2019","year":"(2019)","score":"fresh"},"/m/pain_and_glory":{"name":"Pain and Glory","href":"/m/pain_and_glory","year":"(2019)","score":"fresh"},"/m/joan_of_arc":{"name":"Joan of Arc","href":"/m/joan_of_arc","year":"(2019)","score":"rotten"},"/m/zombi_child":{"name":"Zombi Child","href":"/m/zombi_child","year":"(2019)","score":"fresh"},"/m/the_dead_dont_die_2019":{"name":"The Dead Don't Die","href":"/m/the_dead_dont_die_2019","year":"(2019)","score":"rotten"},"/m/the_projectionist_2020":{"name":"The Projectionist","href":"/m/the_projectionist_2020","year":"(2019)","score":"fresh"},"/m/creed_ii":{"name":"Creed II","href":"/m/creed_ii","year":"(2018)","score":"rotten"},"/m/a_faithful_man":{"name":"A Faithful Man","href":"/m/a_faithful_man","year":"(2018)","score":"rotten"},"/m/a_family_tour":{"name":"A Family Tour","href":"/m/a_family_tour","year":"(2018)","score":"fresh"},"/m/private_life_2018":{"name":"Private Life","href":"/m/private_life_2018","year":"(2018)","score":"rotten"},"/m/ash_is_purest_white":{"name":"Ash Is Purest White","href":"/m/ash_is_purest_white","year":"(2018)","score":"fresh"},"/m/girls_of_the_sun":{"name":"Girls of the Sun","href":"/m/girls_of_the_sun","year":"(2018)","score":"rotten"},"/m/dogman_2019":{"name":"Dogman","href":"/m/dogman_2019","year":"(2018)","score":"rotten"},"/m/the_wild_pear_tree":{"name":"The Wild Pear Tree","href":"/m/the_wild_pear_tree","year":"(2018)","score":"fresh"},"/m/burning_2018":{"name":"Burning","href":"/m/burning_2018","year":"(2018)","score":"fresh"}}