{"/m/midsommar":{"name":"Midsommar","href":"/m/midsommar","year":"(2019)","score":"fresh"},"/m/pokemon_detective_pikachu":{"name":"Pokémon Detective Pikachu","href":"/m/pokemon_detective_pikachu","year":"(2019)","score":"fresh"},"/m/cam":{"name":"Cam","href":"/m/cam","year":"(2018)","score":"fresh"},"/m/the_ballad_of_buster_scruggs":{"name":"The Ballad of Buster Scruggs","href":"/m/the_ballad_of_buster_scruggs","year":"(2018)","score":"fresh"},"/m/apostle_2018":{"name":"Apostle","href":"/m/apostle_2018","year":"(2018)","score":"fresh"},"/m/christopher_robin":{"name":"Christopher Robin","href":"/m/christopher_robin","year":"(2018)","score":"fresh"},"/m/extinction_2018":{"name":"Extinction","href":"/m/extinction_2018","year":"(2018)","score":"fresh"},"/m/unfriended_dark_web":{"name":"Unfriended: Dark Web","href":"/m/unfriended_dark_web","year":"(2018)","score":"fresh"},"/m/upgrade_2018":{"name":"Upgrade","href":"/m/upgrade_2018","year":"(2018)","score":"fresh"},"/m/a_quiet_place_2018":{"name":"A Quiet Place","href":"/m/a_quiet_place_2018","year":"(2018)","score":"fresh"},"/m/mute":{"name":"Mute","href":"/m/mute","year":"(2017)","score":"rotten"},"/m/the_cloverfield_paradox":{"name":"The Cloverfield Paradox","href":"/m/the_cloverfield_paradox","year":"(2018)","score":"rotten"},"/m/creep_2":{"name":"Creep 2","href":"/m/creep_2","year":"(2017)","score":"fresh"},"/m/geralds_game":{"name":"Gerald's Game","href":"/m/geralds_game","year":"(2017)","score":"fresh"},"/m/war_for_the_planet_of_the_apes":{"name":"War for the Planet of the Apes","href":"/m/war_for_the_planet_of_the_apes","year":"(2017)","score":"fresh"},"/m/it_comes_at_night":{"name":"It Comes at Night","href":"/m/it_comes_at_night","year":"(2017)","score":"fresh"},"/m/free_fire":{"name":"Free Fire","href":"/m/free_fire","year":"(2016)","score":"fresh"}}