{"/m/revoir_paris":{"name":"Revoir Paris","href":"/m/revoir_paris","year":"(2022)","score":"fresh"},"/m/barbie":{"name":"Barbie","href":"/m/barbie","year":"(2023)","score":"fresh"},"/m/mission_impossible_dead_reckoning_part_one":{"name":"Mission: Impossible - Dead Reckoning, Part One","href":"/m/mission_impossible_dead_reckoning_part_one","year":"(2023)","score":"fresh"},"/m/inland_2022":{"name":"Inland","href":"/m/inland_2022","year":"(2022)","score":"rotten"},"/m/full_time":{"name":"Full Time","href":"/m/full_time","year":"(2021)","score":"fresh"},"/m/the_eight_mountains":{"name":"The Eight Mountains","href":"/m/the_eight_mountains","year":"(2022)","score":"fresh"},"/m/return_to_seoul":{"name":"Return to Seoul","href":"/m/return_to_seoul","year":"(2022)","score":"fresh"},"/m/how_to_blow_up_a_pipeline":{"name":"How to Blow Up a Pipeline","href":"/m/how_to_blow_up_a_pipeline","year":"(2022)","score":"fresh"},"/m/the_night_of_the_12th":{"name":"The Night of the 12th","href":"/m/the_night_of_the_12th","year":"(2022)","score":"fresh"},"/m/rye_lane":{"name":"Rye Lane","href":"/m/rye_lane","year":"(2023)","score":"fresh"},"/m/the_fabelmans":{"name":"The Fabelmans","href":"/m/the_fabelmans","year":"(2022)","score":"fresh"},"/m/babylon_2022":{"name":"Babylon","href":"/m/babylon_2022","year":"(2022)","score":"fresh"},"/m/blue_jean":{"name":"Blue Jean","href":"/m/blue_jean","year":"(2022)","score":"fresh"},"/m/marcel_the_shell_with_shoes_on":{"name":"Marcel the Shell with Shoes On","href":"/m/marcel_the_shell_with_shoes_on","year":"(2021)","score":"fresh"},"/m/sick_of_myself":{"name":"Sick of Myself","href":"/m/sick_of_myself","year":"(2022)","score":"fresh"},"/m/saint_omer":{"name":"Saint Omer","href":"/m/saint_omer","year":"(2022)","score":"fresh"},"/m/avatar_the_way_of_water":{"name":"Avatar: The Way of Water","href":"/m/avatar_the_way_of_water","year":"(2022)","score":"fresh"},"/m/anais_in_love":{"name":"Anaïs in Love","href":"/m/anais_in_love","year":"(2021)","score":"fresh"},"/m/pleasure_2022":{"name":"Pleasure","href":"/m/pleasure_2022","year":"(2021)","score":"fresh"},"/m/top_gun_maverick":{"name":"Top Gun: Maverick","href":"/m/top_gun_maverick","year":"(2022)","score":"fresh"},"/m/vortex_2021":{"name":"Vortex","href":"/m/vortex_2021","year":"(2021)","score":"fresh"},"/m/the_novice_2021":{"name":"The Novice","href":"/m/the_novice_2021","year":"(2021)","score":"fresh"},"/m/happening":{"name":"Happening","href":"/m/happening","year":"(2021)","score":"fresh"},"/m/william_shakespeares_romeo_and_juliet":{"name":"William Shakespeare's Romeo & Juliet","href":"/m/william_shakespeares_romeo_and_juliet","year":"(1996)","score":"fresh"},"/m/spencer_2021":{"name":"Spencer","href":"/m/spencer_2021","year":"(2021)","score":"fresh"},"/m/last_night_in_soho":{"name":"Last Night in Soho","href":"/m/last_night_in_soho","year":"(2021)","score":"fresh"},"/m/my_name_is_pauli_murray":{"name":"My Name Is Pauli Murray","href":"/m/my_name_is_pauli_murray","year":"(2021)","score":"rotten"},"/m/black_widow_2021":{"name":"Black Widow","href":"/m/black_widow_2021","year":"(2021)","score":"fresh"},"/m/free_solo":{"name":"Free Solo","href":"/m/free_solo","year":"(2018)","score":"fresh"},"/m/black_bear":{"name":"Black Bear","href":"/m/black_bear","year":"(2020)","score":"fresh"},"/m/shiva_baby":{"name":"Shiva Baby","href":"/m/shiva_baby","year":"(2020)","score":"fresh"},"/m/apples":{"name":"Apples","href":"/m/apples","year":"(2020)","score":"fresh"},"/m/sorry_angel":{"name":"Sorry Angel","href":"/m/sorry_angel","year":"(2018)","score":"fresh"},"/m/rocketman_2019":{"name":"Rocketman","href":"/m/rocketman_2019","year":"(2019)","score":"fresh"},"/m/the_aeronauts":{"name":"The Aeronauts","href":"/m/the_aeronauts","year":"(2019)","score":"rotten"},"/m/knock_down_the_house":{"name":"Knock Down the House","href":"/m/knock_down_the_house","year":"(2019)","score":"fresh"},"/m/varda_by_agnes":{"name":"Varda by Agnès","href":"/m/varda_by_agnes","year":"(2019)","score":"fresh"},"/m/pain_and_glory":{"name":"Pain and Glory","href":"/m/pain_and_glory","year":"(2019)","score":"fresh"},"/m/matthias_and_maxime":{"name":"Matthias & Maxime","href":"/m/matthias_and_maxime","year":"(2019)","score":"fresh"},"/m/knives_out":{"name":"Knives Out","href":"/m/knives_out","year":"(2019)","score":"fresh"},"/m/bombshell_2019":{"name":"Bombshell","href":"/m/bombshell_2019","year":"(2019)","score":"rotten"},"/m/another_round":{"name":"Another Round","href":"/m/another_round","year":"(2020)","score":"fresh"},"/m/bridesmaids_2011":{"name":"Bridesmaids","href":"/m/bridesmaids_2011","year":"(2011)","score":"fresh"},"/m/girls_trip":{"name":"Girls Trip","href":"/m/girls_trip","year":"(2017)","score":"fresh"},"/m/lady_bird":{"name":"Lady Bird","href":"/m/lady_bird","year":"(2017)","score":"fresh"},"/m/call_me_by_your_name":{"name":"Call Me by Your Name","href":"/m/call_me_by_your_name","year":"(2017)","score":"fresh"},"/m/the_shape_of_water_2017":{"name":"The Shape of Water","href":"/m/the_shape_of_water_2017","year":"(2017)","score":"fresh"},"/m/the_post":{"name":"The Post","href":"/m/the_post","year":"(2017)","score":"fresh"},"/m/scott_pilgrims_vs_the_world":{"name":"Scott Pilgrim vs. the World","href":"/m/scott_pilgrims_vs_the_world","year":"(2010)","score":"fresh"},"/m/an_education":{"name":"An Education","href":"/m/an_education","year":"(2009)","score":"fresh"}}